seekerdemo/__init__.py
seekerdemo/demolicense.sio
seekerdemo/seekerdemo.cpython-312-linux.so
seekerdemo/seekerdemo.py
seekerdemo-0.0.26.dist-info/licenses/AUTHORS.rst
seekerdemo-0.0.26.dist-info/licenses/LICENSE.rst
seekerdemo-0.0.26.dist-info/METADATA
seekerdemo-0.0.26.dist-info/WHEEL
seekerdemo-0.0.26.dist-info/top_level.txt
seekerdemo-0.0.26.dist-info/RECORD
