Metadata-Version: 2.4
Name: seekerdemo
Version: 0.0.26
Summary: InsideOpt Seeker Demo Distribution
Author: Meinolf Sellmann
Author-email: info@insideopt.com
Keywords: insideopt,seeker,demo,optimization
Classifier: Development Status :: 5 - Production/Stable
Classifier: Intended Audience :: Developers
Classifier: Natural Language :: English
Classifier: Programming Language :: Python :: 3.12
Classifier: Operating System :: POSIX :: Linux
Requires-Python: >=3.12.0
License-File: LICENSE.rst
License-File: AUTHORS.rst
Dynamic: author
Dynamic: author-email
Dynamic: classifier
Dynamic: description
Dynamic: keywords
Dynamic: license-file
Dynamic: requires-python
Dynamic: summary
